gqylpy_ssh/__init__.py
gqylpy_ssh/g ssh.py
gqylpy_ssh-1.2.6.dist-info/LICENSE
gqylpy_ssh-1.2.6.dist-info/METADATA
gqylpy_ssh-1.2.6.dist-info/WHEEL
gqylpy_ssh-1.2.6.dist-info/top_level.txt
gqylpy_ssh-1.2.6.dist-info/RECORD
